rtl/mbist_fsm.v
module mbist_fsm (
    input clk,
    input rst_n, 
    input start_test,
    
    output reg we_out,
    output wire [3:0] addr_out,
    output reg [7:0] data_out,
    input [7:0] data_in,
    
    output reg done_flag,
    output reg err_flag
);

    reg [2:0] state; // 0: idle, 1: write, 2: read_comp, 3: done
    reg [3:0] cnt;
    
    wire [7:0] pat = 8'hAA; 

    // noi truc tiep adr ra ngoai
    assign addr_out = cnt;

    always @(posedge clk or negedge rst_n) begin
        if(!rst_n) begin
            state <= 0;
            cnt <= 0;
            we_out <= 0;
            done_flag <= 0;
            err_flag <= 0;
            // data_out <= 8'd0; 
        end 
        else begin
            case(state)
                0: begin 
                    done_flag <= 0;
                    err_flag <= 0;
                    cnt <= 0;
                    we_out <= 0;
                    if(start_test) state <= 1; // vao trang thai ghi
                end
                
                1: begin 
                    we_out <= 1;
                    data_out <= pat;
                    
                    if(cnt == 15) begin
                        state <= 2;
                        cnt <= 0;
                        we_out <= 0; 
                    end else begin
                        cnt <= cnt + 1;
                    end
                end
                
                2: begin 
                    we_out <= 0;
                    
                    // check error data
                    if(data_in != pat) begin
                        err_flag <= 1;
                        // $display("Error at %d", cnt);
                    end

                    if(cnt == 15) begin
                        state <= 3;
                        cnt <= 0;
                    end else begin
                        cnt <= cnt + 1;
                    end
                end
                
                3: begin // done
                    done_flag <= 1;
                    if(!start_test) state <= 0;
                end
                
                default: state <= 0;
            endcase
        end
    end

endmodule

rtl/sram_16x8.v
module sram_16x8 (
    input clk,
    input we,
    input [3:0] adr,
    input [7:0] din,
    input [1:0] fault,
    output reg [7:0] dout
);

    reg [7:0] mem [0:15];

    always @(posedge clk) begin
        if(we) begin
            mem[adr] <= din;
        end
    end
    always @(*) begin
    	  case(fault)
    	      2'b00: dout = 8'h00;
    	      default: dout = mem[adr]; 
    	  endcase
    end
endmodule

rtl/mbist_top.v
module mbist_top (
    input clk,
    input rst_n,
    input test_en,
    input wire [1:0] fault,
    output done,
    output fail
);

    wire w_en;
    wire [3:0] a_bus;
    wire [7:0] d_to_mem;
    wire [7:0] d_from_mem;

    sram_16x8 sram_inst(
        .clk(clk),
        .we(w_en),
        .adr(a_bus),
        .din(d_to_mem),
        .dout(d_from_mem),
        .fault(fault)
    );

    mbist_fsm ctrl(
        .clk(clk),
        .rst_n(rst_n),
        .start_test(test_en),
        .we_out(w_en),
        .addr_out(a_bus),
        .data_out(d_to_mem),
        .data_in(d_from_mem),
        .done_flag(done),
        .err_flag(fail)
    );

endmodule

rtl/tb_mbist.v
`timescale 1ns / 1ps

module tb_mbist();

    reg clk;
    reg rst_n;
    reg en;
    reg [1:0] fault_ctrl;
    wire d;
    wire f;

    mbist_top dut (
        .clk(clk),
        .rst_n(rst_n),
        .test_en(en),
        .fault(fault_ctrl),
        .done(d),
        .fail(f)
    );

    initial begin
        clk = 0;
        forever #5 clk = ~clk;
    end

    initial begin
        rst_n = 0; 
        en = 0;
        fault_ctrl = 2'b11; // 2'b11: No Fault
        #15;
        rst_n = 1;
        #10;

        $display("=== TEST 1: NORMAL RUN ===");
        en = 1;
        wait(d == 1);
        #10;
        en = 0;
        
        if(!f) $display("-> PASS!");
        else $display("-> FAIL!");

        #30;
        
        $display("=== TEST 2: FAULT INJECTION (Stuck-at Fault) ===");
        // Inject fault directly via backdoor
        fault_ctrl = 2'b00; // 2'b00: Stuck-at
        
        en = 1;
        wait(d == 1);
        #10;
        en = 0;
        
        if(f) $display("-> TEST OK (Fault caught)!");
        else $display("-> TEST FAILED (Fault missed)!");

        #50;
        $finish;
    end
    
    initial begin
        $dumpfile("wave.vcd");
        $dumpvars(0, tb_mbist); 
    end

endmodule

result/wave.vcd
$date
	Fri Jul 24 15:31:45 2026
$end
$version
	Icarus Verilog
$end
$timescale
	1ps
$end
$scope module tb_mbist $end
$var wire 1 ! f $end
$var wire 1 " d $end
$var reg 1 # clk $end
$var reg 1 $ en $end
$var reg 2 % fault_ctrl [1:0] $end
$var reg 1 & rst_n $end
$scope module dut $end
$var wire 1 # clk $end
$var wire 2 ' fault [1:0] $end
$var wire 1 & rst_n $end
$var wire 1 $ test_en $end
$var wire 1 ( w_en $end
$var wire 1 ! fail $end
$var wire 1 " done $end
$var wire 8 ) d_to_mem [7:0] $end
$var wire 8 * d_from_mem [7:0] $end
$var wire 4 + a_bus [3:0] $end
$scope module ctrl $end
$var wire 4 , addr_out [3:0] $end
$var wire 1 # clk $end
$var wire 8 - pat [7:0] $end
$var wire 1 & rst_n $end
$var wire 1 $ start_test $end
$var wire 8 . data_in [7:0] $end
$var reg 4 / cnt [3:0] $end
$var reg 8 0 data_out [7:0] $end
$var reg 1 " done_flag $end
$var reg 1 ! err_flag $end
$var reg 3 1 state [2:0] $end
$var reg 1 ( we_out $end
$upscope $end
$scope module sram_inst $end
$var wire 4 2 adr [3:0] $end
$var wire 1 # clk $end
$var wire 8 3 din [7:0] $end
$var wire 2 4 fault [1:0] $end
$var wire 1 ( we $end
$var reg 8 5 dout [7:0] $end
$upscope $end
$upscope $end
$upscope $end
$enddefinitions $end
$comment Show the parameter values. $end
$dumpall
$end
#0
$dumpvars
bx 5
b11 4
bx 3
b0 2
b0 1
bx 0
b0 /
bx .
b10101010 -
b0 ,
b0 +
bx *
bx )
0(
b11 '
0&
b11 %
0$
0#
0"
0!
$end
#5000
1#
#10000
0#
#15000
1#
1&
#20000
0#
#25000
b1 1
1#
1$
#30000
0#
#35000
b1 +
b1 ,
b1 2
b1 /
b10101010 )
b10101010 0
b10101010 3
1(
1#
#40000
0#
#45000
b10 +
b10 ,
b10 2
b10 /
1#
#50000
0#
#55000
b11 +
b11 ,
b11 2
b11 /
1#
#60000
0#
#65000
b100 +
b100 ,
b100 2
b100 /
1#
#70000
0#
#75000
b101 +
b101 ,
b101 2
b101 /
1#
#80000
0#
#85000
b110 +
b110 ,
b110 2
b110 /
1#
#90000
0#
#95000
b111 +
b111 ,
b111 2
b111 /
1#
#100000
0#
#105000
b1000 +
b1000 ,
b1000 2
b1000 /
1#
#110000
0#
#115000
b1001 +
b1001 ,
b1001 2
b1001 /
1#
#120000
0#
#125000
b1010 +
b1010 ,
b1010 2
b1010 /
1#
#130000
0#
#135000
b1011 +
b1011 ,
b1011 2
b1011 /
1#
#140000
0#
#145000
b1100 +
b1100 ,
b1100 2
b1100 /
1#
#150000
0#
#155000
b1101 +
b1101 ,
b1101 2
b1101 /
1#
#160000
0#
#165000
b1110 +
b1110 ,
b1110 2
b1110 /
1#
#170000
0#
#175000
b1111 +
b1111 ,
b1111 2
b1111 /
1#
#180000
0#
#185000
0(
b0 +
b0 ,
b0 2
b0 /
b10 1
1#
#190000
0#
#195000
b10101010 *
b10101010 .
b10101010 5
b1 +
b1 ,
b1 2
b1 /
1#
#200000
0#
#205000
b10 +
b10 ,
b10 2
b10 /
1#
#210000
0#
#215000
b11 +
b11 ,
b11 2
b11 /
1#
#220000
0#
#225000
b100 +
b100 ,
b100 2
b100 /
1#
#230000
0#
#235000
b101 +
b101 ,
b101 2
b101 /
1#
#240000
0#
#245000
b110 +
b110 ,
b110 2
b110 /
1#
#250000
0#
#255000
b111 +
b111 ,
b111 2
b111 /
1#
#260000
0#
#265000
b1000 +
b1000 ,
b1000 2
b1000 /
1#
#270000
0#
#275000
b1001 +
b1001 ,
b1001 2
b1001 /
1#
#280000
0#
#285000
b1010 +
b1010 ,
b1010 2
b1010 /
1#
#290000
0#
#295000
b1011 +
b1011 ,
b1011 2
b1011 /
1#
#300000
0#
#305000
b1100 +
b1100 ,
b1100 2
b1100 /
1#
#310000
0#
#315000
b1101 +
b1101 ,
b1101 2
b1101 /
1#
#320000
0#
#325000
b1110 +
b1110 ,
b1110 2
b1110 /
1#
#330000
0#
#335000
b1111 +
b1111 ,
b1111 2
b1111 /
1#
#340000
0#
#345000
bx *
bx .
bx 5
b0 +
b0 ,
b0 2
b0 /
b11 1
1#
#350000
0#
#355000
1"
1#
#360000
0#
#365000
b0 1
1#
0$
#370000
0#
#375000
0"
1#
#380000
0#
#385000
1#
#390000
0#
#395000
b1 1
b0 *
b0 .
b0 5
1#
1$
b0 %
b0 '
b0 4
#400000
0#
#405000
b1 +
b1 ,
b1 2
b1 /
1(
1#
#410000
0#
#415000
b10 +
b10 ,
b10 2
b10 /
1#
#420000
0#
#425000
b11 +
b11 ,
b11 2
b11 /
1#
#430000
0#
#435000
b100 +
b100 ,
b100 2
b100 /
1#
#440000
0#
#445000
b101 +
b101 ,
b101 2
b101 /
1#
#450000
0#
#455000
b110 +
b110 ,
b110 2
b110 /
1#
#460000
0#
#465000
b111 +
b111 ,
b111 2
b111 /
1#
#470000
0#
#475000
b1000 +
b1000 ,
b1000 2
b1000 /
1#
#480000
0#
#485000
b1001 +
b1001 ,
b1001 2
b1001 /
1#
#490000
0#
#495000
b1010 +
b1010 ,
b1010 2
b1010 /
1#
#500000
0#
#505000
b1011 +
b1011 ,
b1011 2
b1011 /
1#
#510000
0#
#515000
b1100 +
b1100 ,
b1100 2
b1100 /
1#
#520000
0#
#525000
b1101 +
b1101 ,
b1101 2
b1101 /
1#
#530000
0#
#535000
b1110 +
b1110 ,
b1110 2
b1110 /
1#
#540000
0#
#545000
b1111 +
b1111 ,
b1111 2
b1111 /
1#
#550000
0#
#555000
0(
b0 +
b0 ,
b0 2
b0 /
b10 1
1#
#560000
0#
#565000
b1 +
b1 ,
b1 2
b1 /
1!
1#
#570000
0#
#575000
b10 +
b10 ,
b10 2
b10 /
1#
#580000
0#
#585000
b11 +
b11 ,
b11 2
b11 /
1#
#590000
0#
#595000
b100 +
b100 ,
b100 2
b100 /
1#
#600000
0#
#605000
b101 +
b101 ,
b101 2
b101 /
1#
#610000
0#
#615000
b110 +
b110 ,
b110 2
b110 /
1#
#620000
0#
#625000
b111 +
b111 ,
b111 2
b111 /
1#
#630000
0#
#635000
b1000 +
b1000 ,
b1000 2
b1000 /
1#
#640000
0#
#645000
b1001 +
b1001 ,
b1001 2
b1001 /
1#
#650000
0#
#655000
b1010 +
b1010 ,
b1010 2
b1010 /
1#
#660000
0#
#665000
b1011 +
b1011 ,
b1011 2
b1011 /
1#
#670000
0#
#675000
b1100 +
b1100 ,
b1100 2
b1100 /
1#
#680000
0#
#685000
b1101 +
b1101 ,
b1101 2
b1101 /
1#
#690000
0#
#695000
b1110 +
b1110 ,
b1110 2
b1110 /
1#
#700000
0#
#705000
b1111 +
b1111 ,
b1111 2
b1111 /
1#
#710000
0#
#715000
b0 +
b0 ,
b0 2
b0 /
b11 1
1#
#720000
0#
#725000
1"
1#
#730000
0#
#735000
b0 1
1#
0$
#740000
0#
#745000
0!
0"
1#
